metricd/__init__.py
metricd/collector.py
metricd/metricd.py
metricd/reporter.py
metricd/utils.py
metricd-1.1.2.data/scripts/metricd
metricd-1.1.2.dist-info/DESCRIPTION.rst
metricd-1.1.2.dist-info/METADATA
metricd-1.1.2.dist-info/RECORD
metricd-1.1.2.dist-info/WHEEL
metricd-1.1.2.dist-info/metadata.json
metricd-1.1.2.dist-info/top_level.txt
