Metadata-Version: 2.0
Name: metricd
Version: 1.1.2
Summary: Monitoring agent for collecting and sending metric data
Home-page: https://github.com/o/metric-agent
Author: Osman Ungur
Author-email: osmanungur@gmail.com
License: MIT License
Keywords: monitoring,metric,agent,statistics,devops
Platform: UNKNOWN
Requires-Dist: psutil (>=4.0.0)
Requires-Dist: requests (>=2.9.0)
